README.md
setup.cfg
setup.py
armus/__init__.py
armus/migrations.py
armus.egg-info/PKG-INFO
armus.egg-info/SOURCES.txt
armus.egg-info/dependency_links.txt
armus.egg-info/top_level.txt
bin/create_migration.py