Metadata-Version: 1.0
Name: armus
Version: 0.2.0
Summary: A tool for running migrations
Home-page: https://github.com/ustudio/armus
Author: uStudio
Author-email: dev@ustudio.com
License: UNKNOWN
Platform: UNKNOWN
